karrio/mappers/dpd/__init__.py
karrio/mappers/dpd/mapper.py
karrio/mappers/dpd/proxy.py
karrio/mappers/dpd/settings.py
karrio/plugins/dpd/__init__.py
karrio/providers/dpd/__init__.py
karrio/providers/dpd/error.py
karrio/providers/dpd/tracking.py
karrio/providers/dpd/units.py
karrio/providers/dpd/utils.py
karrio/providers/dpd/shipment/__init__.py
karrio/providers/dpd/shipment/create.py
karrio/schemas/dpd/Authentication20.py
karrio/schemas/dpd/EndOfDayServiceV10.py
karrio/schemas/dpd/LoginServiceV21.py
karrio/schemas/dpd/ParcelLifecycleServiceV20.py
karrio/schemas/dpd/ParcelShopFinderServiceV50.py
karrio/schemas/dpd/ShipmentServiceV33.py
karrio/schemas/dpd/__init__.py
karrio_dpd-2026.1.4.dist-info/METADATA
karrio_dpd-2026.1.4.dist-info/WHEEL
karrio_dpd-2026.1.4.dist-info/entry_points.txt
karrio_dpd-2026.1.4.dist-info/top_level.txt
karrio_dpd-2026.1.4.dist-info/RECORD
